{
  "project_info": {
    "project_number": "880830293299",
    "project_id": "cruditemapp-c3d92",
    "storage_bucket": "cruditemapp-c3d92.firebasestorage.app"
  },
  "client": [
    {
      "client_info": {
        "mobilesdk_app_id": "1:880830293299:android:16321915f41510c8ce0a46",
        "android_client_info": {
          "package_name": "com.example.cruditemapp"
        }
      },
      "oauth_client": [],
      "api_key": [
        {
          "current_key": "AIzaSyDd02M7n5DFjTxFIs1-SrFQUhyKQBBxR0I"
        }
      ],
      "services": {
        "appinvite_service": {
          "other_platform_oauth_client": []
        }
      }
    }
  ],
  "configuration_version": "1"
}